image_compression/__init__.py
image_compression/compression.py
image_compression/utils.py
imagecompression6/__init__.py
imagecompression6/compression.py
imagecompression6/utils.py
imagecompression6-0.1.1.dist-info/LICENSE.txt
imagecompression6-0.1.1.dist-info/METADATA
imagecompression6-0.1.1.dist-info/WHEEL
imagecompression6-0.1.1.dist-info/top_level.txt
imagecompression6-0.1.1.dist-info/RECORD
